EcMasterPython/__init__.py
EcMasterPython/Examples/EcMasterDemoPython/EcDemoApp.py
EcMasterPython/Examples/EcMasterDemoPython/EcDemoAppGui.py
EcMasterPython/Examples/EcMasterDemoPython/EcDemoAppGui.ui
EcMasterPython/Examples/EcMasterDemoPython/EcDemoAppInteractive.py
EcMasterPython/Sources/EcWrapperPython/EcWrapper.py
EcMasterPython/Sources/EcWrapperPython/EcWrapperPython.py
EcMasterPython/Sources/EcWrapperPython/EcWrapperPythonTypes.py
EcMasterPython/Sources/EcWrapperPython/EcWrapperTypes.py
EcMasterPython-3.1.4.4.dist-info/LICENSE
EcMasterPython-3.1.4.4.dist-info/METADATA
EcMasterPython-3.1.4.4.dist-info/WHEEL
EcMasterPython-3.1.4.4.dist-info/top_level.txt
EcMasterPython-3.1.4.4.dist-info/RECORD
