Metadata-Version: 2.1
Name: EcMasterPython
Version: 3.1.4.4
Summary: The Python Wrapper provides a Python interface to use acontis EtherCAT Master (EC-Master), acontis EtherCAT Simulator (EC-Simulator) and RAS Client/Server.
Home-page: https://www.acontis.com/
Author: acontis technologies GmbH
Author-email: ecsupport@acontis.com
License: proprietary and confidential
Project-URL: Programming Interface, https://public.acontis.com/manuals/EC-Master/3.1/html/ec-master-python/index.html
Keywords: Acontis EtherCAT Master Simulator Library
Classifier: Programming Language :: Python
Classifier: Programming Language :: Cython
Classifier: Programming Language :: C
Classifier: Programming Language :: C++
Classifier: Programming Language :: Python :: 3
Classifier: License :: Other/Proprietary License
Classifier: Operating System :: Microsoft :: Windows
Classifier: Operating System :: POSIX :: Linux
Classifier: Operating System :: Unix
Classifier: Topic :: Scientific/Engineering
Classifier: Topic :: Software Development :: Libraries
Classifier: Topic :: System :: Monitoring
Classifier: Topic :: System :: Networking
Requires-Python: >=3.7
License-File: LICENSE
